{
  "_fv": 25,
  "_type": "tool",
  "definition": {
    "renderType": 0,
    "texture": "elucidator",
    "customModelName": "Normal",
    "name": "Elucidator",
    "specialInfo": [
      "The Elucidator is a single-handed powerful sword"
    ],
    "creativeTab": {
      "value": "COMBAT"
    },
    "toolType": "Sword",
    "harvestLevel": 1,
    "efficiency": 4.0,
    "attackSpeed": 1.0,
    "enchantability": 2,
    "damageVsEntity": 4.0,
    "usageCount": 100,
    "blocksAffected": [],
    "hasGlow": false,
    "repairItems": [],
    "immuneToFire": false,
    "stayInGridWhenCrafting": false,
    "damageOnCrafting": false
  }
}